{
    "colorCategory": {
        "patisserieColor": "#FF9F00",
        "boutiqueColor": "#E70012",
        "superatteColor": "#00B242",
        "cafeColor": "#FF7101",
        "pharmacieColor": "#4ca6a6"
    },
    "colorScheme": {
        "background": "#00B242",
        "appbarColor": "#00B242",
        "primaryColor": "#00B242",
        "secondaryColor": "#ffffff",
        "containerColor": "#00B242",
        "containerFadeColor": "#99e0b3",
        "textColor": "#000000",
        "iconColor": "#00B242",
        "iconSecondaryColor": "#ffffff",
        "buttonColor": "#00B242",
        "searchBarColor": "#99e0b3",
        "cardColor": "#99e0b3",
        "deleteColor": "#E70012"
    }
}